{
  "title" : "TechJSON",
  "type" : "object",
  "properties" : {
    "installs" : {
      "type" : "array",
      "items" : {
        "title" : "Install",
        "type" : "object",
        "properties" : {
          "base var" : {
            "type" : "string"
          },
          "path" : {
            "type" : "string"
          }
        }
      }
    },
    "libraries" : {
      "type" : "array",
      "items" : {
        "title" : "Library",
        "type" : "object",
        "properties" : {
          "ccs liberty file" : {
            "type" : "string"
          },
          "ccs library file" : {
            "type" : "string"
          },
          "ecsm liberty file" : {
            "type" : "string"
          },
          "ecsm library file" : {
            "type" : "string"
          },
          "corner" : {
            "title" : "Corner",
            "type" : "object",
            "properties" : {
              "nmos" : {
                "type" : "string"
              },
              "pmos" : {
                "type" : "string"
              },
              "temperature" : {
                "type" : "string"
              }
            }
          },
          "itf files" : {
            "title" : "MinMaxCap",
            "type" : "object",
            "properties" : {
              "max cap" : {
                "type" : "string"
              },
              "min cap" : {
                "type" : "string"
              }
            }
          },
          "lef file" : {
            "type" : "string"
          },
          "gds file" : {
            "type" : "string"
          },
          "metal layers" : {
            "type" : "array",
            "items" : {
              "title" : "MetalLayer",
              "type" : "object",
              "properties" : {
                "name" : {
                  "type" : "string"
                },
                "preferred routing direction" : {
                  "type" : "string"
                }
              }
            }
          },
          "milkyway lib in dir" : {
            "type" : "string"
          },
          "milkyway techfile" : {
            "type" : "string"
          },
          "nldm liberty file" : {
            "type" : "string"
          },
          "nldm library file" : {
            "type" : "string"
          },
          "openaccess techfile" : {
            "type" : "string"
          },
          "provides" : {
            "type" : "array",
            "items" : {
              "title" : "Provide",
              "type" : "object",
              "properties" : {
                "lib_type" : {
                  "type" : "string"
                },
                "vt" : {
                  "type" : "string"
                }
              }
            }
          },
          "qrc techfile" : {
            "type" : "string"
          },
          "supplies" : {
            "title" : "Supplies",
            "type" : "object",
            "properties" : {
              "GND" : {
                "type" : "string"
              },
              "VDD" : {
                "type" : "string"
              }
            }
          },
          "tluplus files" : {
            "title" : "MinMaxCap",
            "type" : "object",
            "properties" : {
              "max cap" : {
                "type" : "string"
              },
              "min cap" : {
                "type" : "string"
              }
            }
          },
          "tluplus map file": {
            "title" : "TLUPlusMapFile",
            "type" : "string"
          },
          "verilog sim" : {
            "type" : "string"
          },
          "verilog synth" : {
            "type" : "string"
          }
        }
      }
    },
    "name" : {
      "type" : "string"
    },
    "gds map file" : {
      "type" : "string"
    },
    "tarballs" : {
      "type" : "array",
      "items" : {
        "title" : "Tarball",
        "type" : "object",
        "properties" : {
          "base var" : {
            "type" : "string"
          },
          "homepage" : {
            "type" : "string"
          },
          "path" : {
            "type" : "string"
          }
        },
        "additionalProperties" : false
      }
    }
  }
}
